YTMonsterClient/YTMonsterClient.py
YTMonsterClient/__init__.py
YTMonsterClient-0.0.2.dist-info/LICENSE
YTMonsterClient-0.0.2.dist-info/METADATA
YTMonsterClient-0.0.2.dist-info/WHEEL
YTMonsterClient-0.0.2.dist-info/top_level.txt
YTMonsterClient-0.0.2.dist-info/RECORD
